fdroid_auto/__init__.py
fdroid_auto/defaults.py
fdroid_auto/fdroid_auto.py
fdroid_auto/packages.py
fdroid_auto/term_args.py
fdroid_auto/version.py
fdroid_auto-1.0.0.dist-info/COPYING
fdroid_auto-1.0.0.dist-info/LICENSE
fdroid_auto-1.0.0.dist-info/METADATA
fdroid_auto-1.0.0.dist-info/WHEEL
fdroid_auto-1.0.0.dist-info/entry_points.txt
fdroid_auto-1.0.0.dist-info/top_level.txt
fdroid_auto-1.0.0.dist-info/RECORD
