Metadata-Version: 2.1
Name: fdroid_auto
Version: 1.0.0
Summary: Little program to automate installation and removal of android apps. 
Author-email: sivefunc <sivefunc@tuta.io>
License: fdroid-auto <-> Automating f-droid from CLI
Project-URL: Homepage, https://codeberg.org/Sivefunc/fdroid_auto
Keywords: linux,android,python3,cli
Classifier: License :: OSI Approved :: GNU General Public License v3 (GPLv3)
Classifier: Programming Language :: Python
Classifier: Programming Language :: Python :: 3
Requires-Python: >=3.11
License-File: LICENSE
License-File: COPYING
Requires-Dist: rich >=13.8.0
